edwh_server_provisioning_plugin/__about__.py
edwh_server_provisioning_plugin/__init__.py
edwh_server_provisioning_plugin/server_provisioning_plugin.py
edwh_server_provisioning_plugin-0.8.0.dist-info/METADATA
edwh_server_provisioning_plugin-0.8.0.dist-info/WHEEL
edwh_server_provisioning_plugin-0.8.0.dist-info/entry_points.txt
edwh_server_provisioning_plugin-0.8.0.dist-info/RECORD
