Metadata-Version: 2.4
Name: edwh-server-provisioning-plugin
Version: 0.8.0
Summary: Fabric-based remote server management plugin for `edwh`
Project-URL: Documentation, https://github.com/educationwarehouse/server_provisioning#readme
Project-URL: Issues, https://github.com/educationwarehouse/server_provisioning/issues
Project-URL: Source, https://github.com/educationwarehouse/server_provisioning
Author-email: Remco Boerma <remco.b@educationwarehouse.nl>, Robin van der Noord <robin.vdn@educationwarehouse.nl>
Classifier: Development Status :: 4 - Beta
Classifier: Programming Language :: Python
Classifier: Programming Language :: Python :: 3.10
Classifier: Programming Language :: Python :: 3.11
Classifier: Programming Language :: Python :: Implementation :: CPython
Classifier: Programming Language :: Python :: Implementation :: PyPy
Requires-Python: >=3.10
Requires-Dist: edwh
Requires-Dist: fabric
Requires-Dist: pyyaml
Requires-Dist: tabulate
Provides-Extra: dev
Requires-Dist: black; extra == 'dev'
Requires-Dist: hatch; extra == 'dev'
